dbt/__init__.py
dbt/adapters/databricks/__init__.py
dbt/adapters/databricks/__version__.py
dbt/adapters/databricks/api_client.py
dbt/adapters/databricks/column.py
dbt/adapters/databricks/connections.py
dbt/adapters/databricks/constants.py
dbt/adapters/databricks/constraints.py
dbt/adapters/databricks/credentials.py
dbt/adapters/databricks/dbr_capabilities.py
dbt/adapters/databricks/global_state.py
dbt/adapters/databricks/handle.py
dbt/adapters/databricks/impl.py
dbt/adapters/databricks/logging.py
dbt/adapters/databricks/parse_model.py
dbt/adapters/databricks/relation.py
dbt/adapters/databricks/utils.py
dbt/adapters/databricks/behaviors/columns.py
dbt/adapters/databricks/catalogs/__init__.py
dbt/adapters/databricks/catalogs/_hive_metastore.py
dbt/adapters/databricks/catalogs/_relation.py
dbt/adapters/databricks/catalogs/_unity.py
dbt/adapters/databricks/events/base.py
dbt/adapters/databricks/events/connection_events.py
dbt/adapters/databricks/events/credential_events.py
dbt/adapters/databricks/events/other_events.py
dbt/adapters/databricks/events/pipeline_events.py
dbt/adapters/databricks/python_models/python_config.py
dbt/adapters/databricks/python_models/python_submissions.py
dbt/adapters/databricks/python_models/run_tracking.py
dbt/adapters/databricks/python_models/util.py
dbt/adapters/databricks/relation_configs/base.py
dbt/adapters/databricks/relation_configs/column_comments.py
dbt/adapters/databricks/relation_configs/column_mask.py
dbt/adapters/databricks/relation_configs/column_tags.py
dbt/adapters/databricks/relation_configs/comment.py
dbt/adapters/databricks/relation_configs/constraints.py
dbt/adapters/databricks/relation_configs/incremental.py
dbt/adapters/databricks/relation_configs/liquid_clustering.py
dbt/adapters/databricks/relation_configs/materialized_view.py
dbt/adapters/databricks/relation_configs/partitioning.py
dbt/adapters/databricks/relation_configs/query.py
dbt/adapters/databricks/relation_configs/refresh.py
dbt_databricks-1.11.0.dist-info/METADATA
dbt_databricks-1.11.0.dist-info/WHEEL
dbt_databricks-1.11.0.dist-info/RECORD
