Metadata-Version: 2.4
Name: dbt-databricks
Version: 1.11.0
Summary: The Databricks adapter plugin for dbt
Project-URL: homepage, https://github.com/databricks/dbt-databricks
Project-URL: changelog, https://github.com/databricks/dbt-databricks/blob/main/CHANGELOG.md
Project-URL: documentation, https://docs.getdbt.com/reference/resource-configs/databricks-configs
Project-URL: issues, https://github.com/databricks/dbt-databricks/issues
Project-URL: repository, https://github.com/databricks/dbt-databricks
Author-email: Databricks <feedback@databricks.com>
License-Expression: Apache-2.0
Classifier: Development Status :: 5 - Production/Stable
Classifier: License :: OSI Approved :: Apache Software License
Classifier: Operating System :: MacOS :: MacOS X
Classifier: Operating System :: Microsoft :: Windows
Classifier: Operating System :: POSIX :: Linux
Classifier: Programming Language :: Python :: 3.10
Classifier: Programming Language :: Python :: 3.11
Classifier: Programming Language :: Python :: 3.12
Classifier: Programming Language :: Python :: 3.13
Requires-Python: >=3.10
Requires-Dist: databricks-sdk<0.68.0,>=0.41
Requires-Dist: databricks-sql-connector[pyarrow]<4.1.4,>=4.1.1
Requires-Dist: dbt-adapters<1.18.0,>=1.17.2
Requires-Dist: dbt-common<2.0.0,>=1.33.0
Requires-Dist: dbt-core<1.11.1,>=1.10.1
Requires-Dist: dbt-spark<1.9.4,>=1.9.0
Requires-Dist: keyring>=23.13.0
Requires-Dist: pydantic>=1.10.0
